hiphp/__init__.py
hiphp/hiphpabout.py
hiphp/hiphpcoding.py
hiphp/hiphpeditor.py
hiphp/hiphpfunc.py
hiphp/hiphphelp.py
hiphp/hiphplicense.py
hiphp/hiphplinkextractor.py
hiphp/hiphplogo.py
hiphp/hiphpmsgs.py
hiphp/hiphpphpfunctions.py
hiphp/hiphpversion.py
hiphp-0.3.6.dist-info/LICENSE
hiphp-0.3.6.dist-info/METADATA
hiphp-0.3.6.dist-info/WHEEL
hiphp-0.3.6.dist-info/top_level.txt
hiphp-0.3.6.dist-info/RECORD
