Metadata-Version: 2.1
Name: hiphp
Version: 0.3.6
Summary: hiphp - free & open source project for create a BackDoor to control PHP-based sites.
Home-page: https://github.com/yasserbdj96/hiphp
Author: yasserbdj96
Author-email: yasser.bdj96@gmail.com
License: MIT License
Project-URL: Source, https://github.com/yasserbdj96/hiphp
Project-URL: WebSite, https://yasserbdj96.github.io/hiphp
Project-URL: Documentation, https://yasserbdj96.github.io/hiphp
Project-URL: Chat, https://gitter.im/yasserbdj96/hiphp
Project-URL: Author WebSite, https://yasserbdj96.github.io/
Project-URL: Sponsor, https://github.com/sponsors/yasserbdj96
Keywords: HIPHP BackDoor,Open-source tool,Remote control,PHP programming,HTTP/HTTPS protocol,POST/GET method,Port 80,File download,File editing,Tor networks,Password protection,Webmasters,Third-party software,User-friendly,Access rights,Directory structure,Flexibility,Security,Compatibility,Content management
Platform: UNKNOWN
Classifier: Environment :: Web Environment
Classifier: Development Status :: 5 - Production/Stable
Classifier: Intended Audience :: Developers
Classifier: Natural Language :: English
Classifier: License :: OSI Approved :: MIT License
Classifier: Programming Language :: Python
Classifier: Programming Language :: Python :: 3
Classifier: Programming Language :: Python :: 3.7
Classifier: Programming Language :: Python :: 3.8
Classifier: Programming Language :: Python :: 3.9
Classifier: Programming Language :: Python :: 3.10
Classifier: Programming Language :: Python :: 3.11
Classifier: Programming Language :: Python :: 3 :: Only
Classifier: Operating System :: Unix
Classifier: Operating System :: MacOS :: MacOS X
Classifier: Operating System :: Microsoft :: Windows
Classifier: Topic :: Software Development :: Build Tools
Classifier: Topic :: Software Development :: Libraries
Classifier: Topic :: Software Development :: Libraries :: Python Modules
Classifier: Topic :: Internet :: WWW/HTTP
License-File: LICENSE
Requires-Dist: requests
Requires-Dist: hexor
Requires-Dist: BeautifulSoup4
